labgsheet/__init__.py
labgsheet/labgsheet.py
labgsheet-0.1.1.dist-info/METADATA
labgsheet-0.1.1.dist-info/RECORD
labgsheet-0.1.1.dist-info/WHEEL
labgsheet-0.1.1.dist-info/top_level.txt
